teachablehub/__init__.py
teachablehub/config.py
teachablehub/clients/__init__.py
teachablehub/clients/base.py
teachablehub/clients/errors.py
teachablehub/clients/management_api.py
teachablehub/clients/prediction_api.py
teachablehub/deployments/__init__.py
teachablehub/deployments/base.py
teachablehub/deployments/ludwig.py
teachablehub/deployments/sklearn.py
teachablehub-1.0.40.dist-info/LICENSE
teachablehub-1.0.40.dist-info/METADATA
teachablehub-1.0.40.dist-info/WHEEL
teachablehub-1.0.40.dist-info/top_level.txt
teachablehub-1.0.40.dist-info/RECORD
