Metadata-Version: 2.1
Name: teachablehub
Version: 1.0.40
Summary: TeachableHub Machine Learning Platform SDK. Deployments, Predictions, and Management.
Home-page: https://github.com/teachablehub/python-sdk
Author: Marian Ignev
Author-email: dev@teachablehub.com
License: UNKNOWN
Keywords: deep learning deep_learning machine machine_learning natural language processing computer vision
Platform: UNKNOWN
Requires-Python: >=3.4
License-File: LICENSE
Requires-Dist: uplink (==0.9.3)
Requires-Dist: th-sklearn-json
Requires-Dist: numpy
